{
  "number": 33,
  "title": "Yaa namaa",
  "category": "salvation",
  "sections": [
    {
      "type": "CHR",
      "lines": [
        "Yaa namaa",
        "Yesus dhufee nu barbaaduu (2)"
      ]
    },
    {
      "type": "VRS1",
      "lines": [
        "Addamii fi Hewaan,",
        "Yesus dhufee nu barbaaduu",
        "Warri keenya duraa,",
        "Yesus dhufee nu barbaaduu",
        "Abboommiii diiganii",
        "Yesus dhufee nu barbaaduu",
        "Mukattii nyaatanii",
        "Yesus dhufee nu barbaaduu",
        "Jannata dhisanii",
        "Yesus dhufee nu barbaaduu",
        "Du'atti kaatan",
        "Yesus dhufee nu barbaaduu"
      ]
    },
    {
      "type": "CHR",
      "lines": [
        "Yaa namaa",
        "Yesus dhufee nu barbaaduu (2)"
      ]
    },
    {
      "type": "VRS2",
      "lines": [
        "Akka Abboota keenya",
        "Yesus dhufee nu barbaaduu",
        "Nu karaa irraa badnaan",
        "Yesus dhufee nu barbaaduu",
        "Nu cubbu hojennaan",
        "Yesus dhufee nu barbaaduu",
        "Uumaattii fagaannaan",
        "Yesus dhufee nu barbaaduu",
        "Badiisaaf qophoofnaan",
        "Yesus dhufee nu barbaaduu",
        "Ilmaan du'aa taanaan",
        "Yesus dhufee nu barbaaduu"
      ]
    },
    {
      "type": "CHR",
      "lines": [
        "Yaa namaa",
        "Yesus dhufee nu barbaaduu (2)"
      ]
    },
    {
      "type": "VRS3",
      "lines": [
        "Teessoo Waaqaa dhiisee",
        "Yesus dhufee nu barbaaduu",
        "Biyya lafaa dhufee",
        "Yesus dhufee nu barbaaduu",
        "Mooraa keessa ciisee",
        "Yesus dhufee nu barbaaduu",
        "Cubbuu keenya ciisee",
        "Yesus dhufee nu barbaaduu",
        "Fayyina nuuf laate",
        "Yesus dhufee nu barbaaduu",
        "Du'atti nu oolche",
        "Yesus dhufee nu barbaaduu"
      ]
    },
    {
      "type": "CHR",
      "lines": [
        "Yaa namaa",
        "Yesus dhufee nu barbaaduu (2)"
      ]
    },
    {
      "type": "VRS4",
      "lines": [
        "Oo'a isaan nu waama",
        "Yesus dhufee nu barbaaduu",
        "Eessa jirtuu jedhee",
        "Yesus dhufee nu barbaaduu",
        "Maalif joortu jedhee",
        "Yesus dhufee nu barbaaduu",
        "Dafaaa kottaa jedhee",
        "Ba'aa keessan hundaa",
        "Yesus dhufee nu barbaaduu",
        "Ani nan baadha jedhee",
        "Yesus dhufee nu barbaaduu"
      ]
    },
    {
      "type": "CHR",
      "lines": [
        "Yaa namaa",
        "Yesus dhufee nu barbaaduu (2)"
      ]
    }
  ]
}
