{
  "number": 178,
  "title": "Innoo jiraataadhaa yaadadhaa (2)",
  "sections": [
    {
      "type": "CHR",
      "lines": [
        "Innoo jiraataadhaa yaadadhaa (2)",
        "Gooftaa Yesus biraa",
        "fayyina fudhadhaa,",
        "Inni fannoo gubbaatti",
        "dhiiga isaa lolaase, Isin waamaa jira harka isaa bal'isee."
      ]
    },
    {
      "type": "VRS1",
      "lines": [
        "Ilma Waaqayyo Abbaa",
        "ta'ee utuu jiruu,",
        "Ulfina isaa dhisee",
        "namoota fayyisuuf,",
        "Cubbu utuu hin qabaatin",
        "cubbamootaaf jedhee,",
        "Dhiiga isaa lolaase",
        "fannoo irratti nuuf du'e."
      ]
    },
    {
      "type": "CHR",
      "lines": [
        "Innoo jiraataadhaa yaadadhaa (2)",
        "Gooftaa Yesus biraa",
        "fayyina fudhadhaa,",
        "Inni fannoo gubbaatti",
        "dhiiga isaa lolaase, Isin waamaa jira harka isaa bal'isee."
      ]
    },
    {
      "type": "VRS2",
      "lines": [
        "Kottaa yaa namootaa",
        "har'a walii gallaa,",
        "Qalbii diddiirrannee",
        "gara Gooftaa dhaqnaa,",
        "Amma iyyuu nu wwama",
        "harka isaa bal'isee,",
        "Nu fayyisuuf jedhee",
        "dhiiga isaa lolaasee."
      ]
    },
    {
      "type": "CHR",
      "lines": [
        "Innoo jiraataadhaa yaadadhaa (2)",
        "Gooftaa Yesus biraa",
        "fayyina fudhadhaa,",
        "Inni fannoo gubbaatti",
        "dhiiga isaa lolaase, Isin waamaa jira harka isaa bal'isee."
      ]
    },
    {
      "type": "VRS3",
      "lines": [
        "Gooftaan keenya Yesus",
        "nu barbaaduu dhufee,",
        "Nu'i maaliif badna",
        "cubbuudhaan qabamnee?",
        "Kottaa yaa obbolootaa",
        "gara isatti deebinaa,",
        "Isa bira dhaqnaan fayyina argatnaa."
      ]
    },
    {
      "type": "CHR",
      "lines": [
        "Innoo jiraataadhaa yaadadhaa (2)",
        "Gooftaa Yesus biraa",
        "fayyina fudhadhaa,",
        "Inni fannoo gubbaatti",
        "dhiiga isaa lolaase, Isin waamaa jira harka isaa bal'isee."
      ]
    },
    {
      "type": "VRS4",
      "lines": [
        "Warri Gooftaa amantan",
        "baay'ee kan gammaddan,",
        "Harka Waaqayyoo irraa",
        "nyaattanii kan dhugdan,",
        "Dhiiphinni yoo dhufe",
        "booddee hin deebi'inaa"
      ]
    },
    {
      "type": "CHR",
      "lines": [
        "Innoo jiraataadhaa yaadadhaa (2)",
        "Gooftaa Yesus biraa",
        "fayyina fudhadhaa,",
        "Inni fannoo gubbaatti",
        "dhiiga isaa lolaase, Isin waamaa jira harka isaa bal'isee."
      ]
    }
  ]
}