{
  "number": 75,
  "title": "Yaa Gooftaa koo garaa koo in beekta,",
  "sections": [
    {
      "type": "VRS1",
      "lines": [
        "Yaa Gooftaa koo garaa koo in beekta,",
        "Taa'uu kootiif ka'uu kooyis,",
        "Yaada koo hundumaa beekta,",
        "Yaada koo fagootti hubatta."
      ]
    },
    {
      "type": "CHR",
      "lines": [
        "Na ilaalta garaas in qorta",
        "Dhoksaa yaada koo in argita,",
        "Gara cubbuutti yoon adeeme,",
        "Gara jireenyaatti na geessi."
      ]
    },
    {
      "type": "VRS2",
      "lines": [
        "Dubbii koo dhoksuun naaf hin ta'u",
        "Yaada garaa namaas beekta,",
        "Beekumsi kee ana dinqa,",
        "Hubachuufis hin danda'u."
      ]
    },
    {
      "type": "CHR",
      "lines": [
        "Na ilaalta garaas in qorta",
        "Dhoksaa yaada koo in argita,",
        "Gara cubbuutti yoon adeeme,",
        "Gara jireenyaatti na geessi."
      ]
    },
    {
      "type": "VRS3",
      "lines": [
        "Homaa si dhoksuu hin danda'u,",
        "Dukkana fagoo keessa illee,",
        "Dukkanichis ifni guyyaas,",
        "Lamaanuu siif tokkicha'oo."
      ]
    },
    {
      "type": "CHR",
      "lines": [
        "Na ilaalta garaas in qorta",
        "Dhoksaa yaada koo in argita,",
        "Gara cubbuutti yoon adeeme,",
        "Gara jireenyaatti na geessi."
      ]
    }
  ]
}