{
  "number": 296,
  "title": "Waaqayyoon in galateeffanna,",
  "category": "worship",
  "sections": [
    {
      "type": "CHR",
      "lines": [
        "Waaqayyoon in galateeffanna,",
        "Guddifnee gammachuun faarfanna,",
        "Hooqubaa isaaf galchina /2/"
      ]
    },
    {
      "type": "VRS1",
      "lines": [
        "Inni kophaa Waaqqayyo dha,",
        "Guddinaanis jabaataa dha,",
        "Aangoo isaatiin mul'ataa dha,",
        "Bara baraan ulfaataa dha."
      ]
    },
    {
      "type": "CHR",
      "lines": [
        "Waaqayyoon in galateeffanna,",
        "Guddifnee gammachuun faarfanna,",
        "Hooqubaa isaaf galchina /2/"
      ]
    },
    {
      "type": "VRS2",
      "lines": [
        "Inni Dugumaan Gooftaa dha,",
        "Deegaa fi rakkataa gargaaraa dha,",
        "Bara baraan mul'ataa dha,",
        "Guddinaanis ulfaataa dha"
      ]
    },
    {
      "type": "CHR",
      "lines": [
        "Waaqayyoon in galateeffanna,",
        "Guddifnee gammachuun faarfanna,",
        "Hooqubaa isaaf galchina /2/"
      ]
    },
    {
      "type": "VRS3",
      "lines": [
        "Kophaa isaa dinqii in godha,",
        "Inni Waaqayyo jiraataa dha,",
        "Inni dhugumaan ulfaataa dha,",
        "Galatni isaaf kan ta'uu dha"
      ]
    },
    {
      "type": "CHR",
      "lines": [
        "Waaqayyoon in galateeffanna,",
        "Guddifnee gammachuun faarfanna,",
        "Hooqubaa isaaf galchina /2/"
      ]
    },
    {
      "type": "VRS4",
      "lines": [
        "Inni anaaf gaachana,",
        "Na eeguudhaaf inni jagna,",
        "Kophaa isaattin Waaqayyoo dha,",
        "Ulfinaanis mul'ataa dha."
      ]
    },
    {
      "type": "CHR",
      "lines": [
        "Waaqayyoon in galateeffanna,",
        "Guddifnee gammachuun faarfanna,",
        "Hooqubaa isaaf galchina /2/"
      ]
    }
  ]
}
